seq_tool/__init__.py
seq_tool/command_line_interface.py
seq_tool/data_processing.py
seq_tool/graphical_interface.py
seq_tool/gsp_algorithm.py
seq_tool/utils.py
seq_tool-0.0.4.dist-info/LICENSE
seq_tool-0.0.4.dist-info/METADATA
seq_tool-0.0.4.dist-info/WHEEL
seq_tool-0.0.4.dist-info/entry_points.txt
seq_tool-0.0.4.dist-info/top_level.txt
seq_tool-0.0.4.dist-info/RECORD
