Metadata-Version: 2.1
Name: seq_tool
Version: 0.0.4
Summary: A Python package implementing the Generalized Sequential Pattern (GSP) algorithm with concurrency support.
Author-email: Peyton Lyons <plyons14@fordham.edu>, Jonathan Mele <jmele3@fordham.edu>, Michael Sluck <msluck@fordham.edu>, Cody Chen <cchen187@fordham.edu>, Fiza Metla <fmetla@fordham.edu>, James Guest <jguest2@fordham.edu>, Mario Marku <mmarku@fordham.edu>
License: MIT License
Project-URL: Homepage, https://www.cis.fordham.edu/edmlab/software/course-sequence-analysis
Project-URL: Bug Tracker, https://github.com/Fordham-EDM-Lab/CSAT/issues
Classifier: Programming Language :: Python :: 3
Classifier: License :: OSI Approved :: MIT License
Classifier: Operating System :: OS Independent
Requires-Python: >=3.10
License-File: LICENSE
Requires-Dist: bottleneck ==1.3.7
Requires-Dist: numexpr ==2.8.7
Requires-Dist: numpy ==1.25.2
Requires-Dist: pandas ==2.2.1
Requires-Dist: python-dateutil ==2.8.2
Requires-Dist: pytz ==2024.1
Requires-Dist: setuptools ==68.2.2
Requires-Dist: six ==1.16.0
Requires-Dist: wheel ==0.41.2
Requires-Dist: dateparser ==1.2.0
